main/__init__.py
main/findNplot.py
findNplot-0.1.0.dist-info/LICENSE.txt
findNplot-0.1.0.dist-info/METADATA
findNplot-0.1.0.dist-info/WHEEL
findNplot-0.1.0.dist-info/top_level.txt
findNplot-0.1.0.dist-info/RECORD
