Metadata-Version: 2.1
Name: findNplot
Version: 0.1.0
Summary: A program to access an excel sheet and extract elements of a single column and plot them
Author: Sushruta Das
Author-email: sushrutadas@gmail.com
Classifier: Programming Language :: Python :: 3
Classifier: License :: OSI Approved :: MIT License
Classifier: Operating System :: OS Independent
Requires-Python: >=3.10.11
License-File: LICENSE.txt
Requires-Dist: pandas
Requires-Dist: matplotlib
Requires-Dist: numpy
Requires-Dist: twine
